CHANGES.txt
LICENSE.txt
MANIFEST.in
README.txt
TODO.txt
bootstrap.py
buildout.cfg
setup.py
docs/_sources/README.txt
docs/_sources/index.txt
docs/_sources/tests/advanced.txt
docs/_sources/tests/batching.txt
docs/_sources/tests/client.txt
docs/_sources/tests/container.txt
docs/_sources/tests/geo.txt
docs/_sources/tests/geopoint.txt
docs/_sources/tests/object.txt
docs/_sources/tests/shared.txt
docs/_sources/tests/storage.txt
docs/_sources/tests/testing.txt
docs/_sources/tests/usecase.txt
docs/_sources/tests/util.txt
docs/_sources/tests/zope.schema.txt
eggs/BTrees-4.11.2-py3.10-win-amd64.egg/EGG-INFO/LICENSE.txt
eggs/BTrees-4.11.2-py3.10-win-amd64.egg/EGG-INFO/requires.txt
eggs/BTrees-4.11.2-py3.10-win-amd64.egg/EGG-INFO/top_level.txt
eggs/MarkupSafe-3.0.2-py3.10-win-amd64.egg/EGG-INFO/LICENSE.txt
eggs/MarkupSafe-3.0.2-py3.10-win-amd64.egg/EGG-INFO/top_level.txt
eggs/Pygments-2.1.3-py3.10.egg/EGG-INFO/entry_points.txt
eggs/Pygments-2.1.3-py3.10.egg/EGG-INFO/top_level.txt
eggs/Sphinx-1.8.5-py3.10.egg/EGG-INFO/entry_points.txt
eggs/Sphinx-1.8.5-py3.10.egg/EGG-INFO/requires.txt
eggs/Sphinx-1.8.5-py3.10.egg/EGG-INFO/top_level.txt
eggs/ZConfig-3.6.1-py3.10.egg/EGG-INFO/LICENSE.txt
eggs/ZConfig-3.6.1-py3.10.egg/EGG-INFO/entry_points.txt
eggs/ZConfig-3.6.1-py3.10.egg/EGG-INFO/requires.txt
eggs/ZConfig-3.6.1-py3.10.egg/EGG-INFO/top_level.txt
eggs/ZConfig-3.6.1-py3.10.egg/ZConfig/schemaless.txt
eggs/ZConfig-3.6.1-py3.10.egg/ZConfig/tests/input/non-ascii.txt
eggs/ZConfig-3.6.1-py3.10.egg/ZConfig/tests/library/README.txt
eggs/ZConfig-3.6.1-py3.10.egg/ZConfig/tests/zipsource/README.txt
eggs/ZODB-5.8.1-py3.10.egg/EGG-INFO/LICENSE.txt
eggs/ZODB-5.8.1-py3.10.egg/EGG-INFO/entry_points.txt
eggs/ZODB-5.8.1-py3.10.egg/EGG-INFO/requires.txt
eggs/ZODB-5.8.1-py3.10.egg/EGG-INFO/top_level.txt
eggs/ZODB-5.8.1-py3.10.egg/ZODB/FileStorage/zconfig.txt
eggs/ZODB-5.8.1-py3.10.egg/ZODB/scripts/README.txt
eggs/ZODB-5.8.1-py3.10.egg/ZODB/scripts/tests/fstail.txt
eggs/ZODB-5.8.1-py3.10.egg/ZODB/scripts/tests/referrers.txt
eggs/ZODB-5.8.1-py3.10.egg/ZODB/tests/blob_basic.txt
eggs/ZODB-5.8.1-py3.10.egg/ZODB/tests/blob_connection.txt
eggs/ZODB-5.8.1-py3.10.egg/ZODB/tests/blob_consume.txt
eggs/ZODB-5.8.1-py3.10.egg/ZODB/tests/blob_importexport.txt
eggs/ZODB-5.8.1-py3.10.egg/ZODB/tests/blob_layout.txt
eggs/ZODB-5.8.1-py3.10.egg/ZODB/tests/blob_packing.txt
eggs/ZODB-5.8.1-py3.10.egg/ZODB/tests/blob_tempdir.txt
eggs/ZODB-5.8.1-py3.10.egg/ZODB/tests/blob_transaction.txt
eggs/ZODB-5.8.1-py3.10.egg/ZODB/tests/blobstorage_packing.txt
eggs/ZODB-5.8.1-py3.10.egg/ZODB/tests/dbopen.txt
eggs/ZODB-5.8.1-py3.10.egg/ZODB/tests/multidb.txt
eggs/ZODB-5.8.1-py3.10.egg/ZODB/tests/synchronizers.txt
eggs/ZODB-5.8.1-py3.10.egg/ZODB/tests/testConnectionSavepoint.txt
eggs/alabaster-0.7.16-py3.10.egg/EGG-INFO/entry_points.txt
eggs/babel-2.17.0-py3.10.egg/EGG-INFO/entry_points.txt
eggs/babel-2.17.0-py3.10.egg/EGG-INFO/requires.txt
eggs/babel-2.17.0-py3.10.egg/EGG-INFO/top_level.txt
eggs/btrees-4.4.0-py3.10-win-amd64.egg/BTrees/Development.txt
eggs/btrees-4.4.0-py3.10-win-amd64.egg/EGG-INFO/SOURCES.txt
eggs/btrees-4.4.0-py3.10-win-amd64.egg/EGG-INFO/dependency_links.txt
eggs/btrees-4.4.0-py3.10-win-amd64.egg/EGG-INFO/entry_points.txt
eggs/btrees-4.4.0-py3.10-win-amd64.egg/EGG-INFO/native_libs.txt
eggs/btrees-4.4.0-py3.10-win-amd64.egg/EGG-INFO/requires.txt
eggs/btrees-4.4.0-py3.10-win-amd64.egg/EGG-INFO/top_level.txt
eggs/certifi-2025.6.15-py3.10.egg/EGG-INFO/top_level.txt
eggs/certifi-2025.7.9-py3.10.egg/EGG-INFO/top_level.txt
eggs/certifi-2025.8.3-py3.10.egg/EGG-INFO/top_level.txt
eggs/cffi-1.17.1-py3.10-win-amd64.egg/EGG-INFO/entry_points.txt
eggs/cffi-1.17.1-py3.10-win-amd64.egg/EGG-INFO/requires.txt
eggs/cffi-1.17.1-py3.10-win-amd64.egg/EGG-INFO/top_level.txt
eggs/cffi-2.0.0-py3.10-win-amd64.egg/EGG-INFO/entry_points.txt
eggs/cffi-2.0.0-py3.10-win-amd64.egg/EGG-INFO/requires.txt
eggs/cffi-2.0.0-py3.10-win-amd64.egg/EGG-INFO/top_level.txt
eggs/charset_normalizer-3.4.2-py3.10-win-amd64.egg/EGG-INFO/entry_points.txt
eggs/charset_normalizer-3.4.2-py3.10-win-amd64.egg/EGG-INFO/requires.txt
eggs/charset_normalizer-3.4.2-py3.10-win-amd64.egg/EGG-INFO/top_level.txt
eggs/charset_normalizer-3.4.3-py3.10-win-amd64.egg/EGG-INFO/entry_points.txt
eggs/charset_normalizer-3.4.3-py3.10-win-amd64.egg/EGG-INFO/requires.txt
eggs/charset_normalizer-3.4.3-py3.10-win-amd64.egg/EGG-INFO/top_level.txt
eggs/colorama-0.4.6-py3.10.egg/EGG-INFO/licenses/LICENSE.txt
eggs/docutils-0.18.1-py3.10.egg/EGG-INFO/COPYING.txt
eggs/docutils-0.18.1-py3.10.egg/EGG-INFO/top_level.txt
eggs/docutils-0.18.1-py3.10.egg/docutils/parsers/rst/include/README.txt
eggs/docutils-0.18.1-py3.10.egg/docutils/parsers/rst/include/isoamsa.txt
eggs/future-1.0.0-py3.10.egg/EGG-INFO/LICENSE.txt
eggs/future-1.0.0-py3.10.egg/EGG-INFO/entry_points.txt
eggs/future-1.0.0-py3.10.egg/EGG-INFO/top_level.txt
eggs/idna-3.10-py3.10.egg/EGG-INFO/requires.txt
eggs/imagesize-1.4.1-py3.10.egg/EGG-INFO/top_level.txt
eggs/jinja2-3.1.6-py3.10.egg/EGG-INFO/entry_points.txt
eggs/jinja2-3.1.6-py3.10.egg/EGG-INFO/requires.txt
eggs/jinja2-3.1.6-py3.10.egg/EGG-INFO/licenses/LICENSE.txt
eggs/m01.fake-3.13.2-py3.10.egg/EGG-INFO/SOURCES.txt
eggs/m01.fake-3.13.2-py3.10.egg/EGG-INFO/dependency_links.txt
eggs/m01.fake-3.13.2-py3.10.egg/EGG-INFO/namespace_packages.txt
eggs/m01.fake-3.13.2-py3.10.egg/EGG-INFO/requires.txt
eggs/m01.fake-3.13.2-py3.10.egg/EGG-INFO/top_level.txt
eggs/m01.fake-3.13.3-py3.10.egg/EGG-INFO/SOURCES.txt
eggs/m01.fake-3.13.3-py3.10.egg/EGG-INFO/dependency_links.txt
eggs/m01.fake-3.13.3-py3.10.egg/EGG-INFO/namespace_packages.txt
eggs/m01.fake-3.13.3-py3.10.egg/EGG-INFO/requires.txt
eggs/m01.fake-3.13.3-py3.10.egg/EGG-INFO/top_level.txt
eggs/m01.stub-3.13.0-py3.10.egg/EGG-INFO/SOURCES.txt
eggs/m01.stub-3.13.0-py3.10.egg/EGG-INFO/dependency_links.txt
eggs/m01.stub-3.13.0-py3.10.egg/EGG-INFO/namespace_packages.txt
eggs/m01.stub-3.13.0-py3.10.egg/EGG-INFO/requires.txt
eggs/m01.stub-3.13.0-py3.10.egg/EGG-INFO/top_level.txt
